pvandyken/deprecated/__init__.py
pvandyken/deprecated/deprecated.py
pvandyken/deprecated/py.typed
pvandyken_deprecated-0.0.4.dist-info/LICENSE
pvandyken_deprecated-0.0.4.dist-info/METADATA
pvandyken_deprecated-0.0.4.dist-info/WHEEL
pvandyken_deprecated-0.0.4.dist-info/RECORD
