Metadata-Version: 2.1
Name: pvandyken-deprecated
Version: 0.0.4
Summary: Wrapper to manage deprecations
License: Apache-2.0
Author: Peter Van Dyken
Author-email: pvandyk2@uwo.ca
Requires-Python: >=3.8
Classifier: License :: OSI Approved :: Apache Software License
Classifier: Programming Language :: Python :: 3
Classifier: Programming Language :: Python :: 3.8
Classifier: Programming Language :: Python :: 3.9
Classifier: Programming Language :: Python :: 3.10
Classifier: Programming Language :: Python :: 3.11
Requires-Dist: packaging (>=22.0)
Requires-Dist: typing-extensions (>=3.10.0)
